imaplibext/__init__.py
imaplibext/_imaplibext.py
imaplibext/__pycache__/__init__.cpython-37.pyc
imaplibext/__pycache__/_imaplibext.cpython-37.pyc
imaplibext-0.7.9.dist-info/LICENSE
imaplibext-0.7.9.dist-info/METADATA
imaplibext-0.7.9.dist-info/WHEEL
imaplibext-0.7.9.dist-info/top_level.txt
imaplibext-0.7.9.dist-info/RECORD
