Metadata-Version: 2.1
Name: imaplibext
Version: 0.7.9
Summary: An imaplib extension module, that provides versions of IMAP4 and IMAP4_SSL with UID-based functions.
Home-page: https://gitlab.com/teward/imaplibext
Author: Thomas Ward
Author-email: teward@dark-net.io
License: AGPLv3+
Download-URL: https://pypi.python.org/pypi/imaplibext
Keywords: imaplib imap UID email
Platform: any
Classifier: Development Status :: 5 - Production/Stable
Classifier: Environment :: Console
Classifier: Environment :: Other Environment
Classifier: Intended Audience :: Developers
Classifier: License :: OSI Approved :: GNU Affero General Public License v3 or later (AGPLv3+)
Classifier: Operating System :: OS Independent
Classifier: Programming Language :: Python
Classifier: Programming Language :: Python :: 2
Classifier: Programming Language :: Python :: 2.6
Classifier: Programming Language :: Python :: 2.7
Classifier: Programming Language :: Python :: 3
Classifier: Programming Language :: Python :: 3.5
Classifier: Programming Language :: Python :: 3.6
Classifier: Programming Language :: Python :: 3.7
Classifier: Topic :: Communications :: Email
Classifier: Topic :: Software Development :: Libraries :: Python Modules
Requires-Dist: typing
